inye_adk/__init__.py
inye_adk/__main__.py
inye_adk/cli.py
inye_adk/templates/commands/inye/intent.md
inye_adk-0.2.0.dist-info/METADATA
inye_adk-0.2.0.dist-info/WHEEL
inye_adk-0.2.0.dist-info/entry_points.txt
inye_adk-0.2.0.dist-info/licenses/LICENSE
inye_adk-0.2.0.dist-info/RECORD
