Metadata-Version: 2.4
Name: inye-adk
Version: 0.2.0
Summary: Inye Agentic Development Kit - Intent clarification command for Claude Code
Project-URL: Homepage, https://github.com/iyeaaa/inye-adk
Project-URL: Repository, https://github.com/iyeaaa/inye-adk
Project-URL: Issues, https://github.com/iyeaaa/inye-adk/issues
Author: iyeaaa
License-Expression: MIT
License-File: LICENSE
Keywords: adk,agent,ai,claude,claude-code,intent
Classifier: Development Status :: 3 - Alpha
Classifier: Environment :: Console
Classifier: Intended Audience :: Developers
Classifier: License :: OSI Approved :: MIT License
Classifier: Programming Language :: Python :: 3
Classifier: Programming Language :: Python :: 3.10
Classifier: Programming Language :: Python :: 3.11
Classifier: Programming Language :: Python :: 3.12
Classifier: Programming Language :: Python :: 3.13
Classifier: Topic :: Software Development :: Libraries :: Python Modules
Requires-Python: >=3.10
Requires-Dist: click>=8.0.0
Requires-Dist: rich>=13.0.0
